rgb2mqtt/__init__.py
rgb2mqtt/device.py
rgb2mqtt/run.py
rgb2mqtt/setup.py
rgb2mqtt/utils.py
rgb2mqtt-1.1.0.dist-info/LICENSE
rgb2mqtt-1.1.0.dist-info/METADATA
rgb2mqtt-1.1.0.dist-info/WHEEL
rgb2mqtt-1.1.0.dist-info/entry_points.txt
rgb2mqtt-1.1.0.dist-info/top_level.txt
rgb2mqtt-1.1.0.dist-info/RECORD
