Metadata-Version: 2.1
Name: rgb2mqtt
Version: 1.1.0
Summary: Python script to make OpenRGB lights available in MQTT
Author-email: Ruben Peters <rubenpeters91@protonmail.com>
License: MIT
Project-URL: Homepage, https://github.com/rubenpeters91/rgb2mqtt
Classifier: Programming Language :: Python :: 3
Classifier: License :: OSI Approved :: MIT License
Classifier: Topic :: Home Automation
Requires-Python: >=3.7
License-File: LICENSE
Requires-Dist: paho-mqtt ~=1.6
Requires-Dist: openrgb-python ~=0.2
Requires-Dist: tomli-w ~=1.0
Provides-Extra: dev
Requires-Dist: black ; extra == 'dev'
Requires-Dist: ruff ; extra == 'dev'
Requires-Dist: isort ; extra == 'dev'
Provides-Extra: test
Requires-Dist: pytest ; extra == 'test'
Requires-Dist: pytest-cov ; extra == 'test'
